pixelarrayllm/__init__.py
pixelarrayllm/client.py
pixelarrayllm/cosyvoice_v2_manager.py
pixelarrayllm/llm_call_manager.py
pixelarrayllm/usage_stats.py
pixelarrayllm-1.0.3.dist-info/licenses/LICENSE
pixelarrayllm-1.0.3.dist-info/METADATA
pixelarrayllm-1.0.3.dist-info/WHEEL
pixelarrayllm-1.0.3.dist-info/top_level.txt
pixelarrayllm-1.0.3.dist-info/RECORD
