Metadata-Version: 2.4
Name: pixelarrayllm
Version: 1.0.3
Summary: PixelArray LLM微服务客户端
Author-email: Lu qi <qi.lu@pixelarrayai.com>
License-Expression: MIT
Keywords: python,llm,ai,pixelarray,client
Classifier: Development Status :: 4 - Beta
Classifier: Intended Audience :: Developers
Classifier: Operating System :: OS Independent
Classifier: Programming Language :: Python :: 3
Classifier: Programming Language :: Python :: 3.8
Classifier: Programming Language :: Python :: 3.9
Classifier: Programming Language :: Python :: 3.10
Classifier: Programming Language :: Python :: 3.11
Classifier: Programming Language :: Python :: 3.12
Classifier: Programming Language :: Python :: 3.13
Classifier: Topic :: Software Development :: Libraries :: Python Modules
Classifier: Topic :: Utilities
Requires-Python: >=3.8
License-File: LICENSE
Requires-Dist: requests
Requires-Dist: aiohttp
Requires-Dist: asyncio
Dynamic: license-file
